llama_index/callbacks/opik/__init__.py
llama_index/callbacks/opik/base.py
llama_index_callbacks_opik-1.2.1.dist-info/METADATA
llama_index_callbacks_opik-1.2.1.dist-info/WHEEL
llama_index_callbacks_opik-1.2.1.dist-info/licenses/LICENSE
llama_index_callbacks_opik-1.2.1.dist-info/RECORD
