Metadata-Version: 2.4
Name: llama-index-callbacks-opik
Version: 1.2.1
Summary: llama-index callbacks Opik Comet integration
Author-email: Jacques VERRE <jacques@comet.com>
License-Expression: MIT
License-File: LICENSE
Requires-Python: <4.0,>=3.9
Requires-Dist: llama-index-core<0.15,>=0.13.0
